cosmicfrog/__init__.py
cosmicfrog/cascadeActions.py
cosmicfrog/db_helpers.py
cosmicfrog/frog_activity_status.py
cosmicfrog/frog_anura.py
cosmicfrog/frog_custom_tables_and_columns.py
cosmicfrog/frog_data.py
cosmicfrog/frog_dbtools.py
cosmicfrog/frog_launcher.py
cosmicfrog/frog_log.py
cosmicfrog/frog_notifications.py
cosmicfrog/frog_params.py
cosmicfrog/frog_platform.py
cosmicfrog/frog_run_scenario.py
cosmicfrog/frog_scenariohelper.py
cosmicfrog/frog_security.py
cosmicfrog/frog_utilitydetails.py
cosmicfrog/frog_utils.py
cosmicfrog/anura28/__init__.py
cosmicfrog/anura28/anuraMasterTableList.json
cosmicfrog/anura28/anuraMasterTablesMappings.json
cosmicfrog/anura28/table_definitions/__init__.py
cosmicfrog/anura28/table_definitions/anura_AdvancedQueueingDetails.json
cosmicfrog/anura28/table_definitions/anura_Analytics.json
cosmicfrog/anura28/table_definitions/anura_BillsOfMaterials.json
cosmicfrog/anura28/table_definitions/anura_BusinessCalendars.json
cosmicfrog/anura28/table_definitions/anura_BusinessHours.json
cosmicfrog/anura28/table_definitions/anura_CategoricalDistributions.json
cosmicfrog/anura28/table_definitions/anura_ChangeoverTimes.json
cosmicfrog/anura28/table_definitions/anura_CustomSimulationScripts.json
cosmicfrog/anura28/table_definitions/anura_CustomerDemand.json
cosmicfrog/anura28/table_definitions/anura_CustomerDemandOriginConstraints.json
cosmicfrog/anura28/table_definitions/anura_CustomerFulfillmentPolicies.json
cosmicfrog/anura28/table_definitions/anura_CustomerFulfillmentPoliciesMultiTimePeriod.json
cosmicfrog/anura28/table_definitions/anura_CustomerOrderProfiles.json
cosmicfrog/anura28/table_definitions/anura_CustomerOrders.json
cosmicfrog/anura28/table_definitions/anura_CustomerRiskConfigurations.json
cosmicfrog/anura28/table_definitions/anura_CustomerTransitConstraints.json
cosmicfrog/anura28/table_definitions/anura_Customers.json
cosmicfrog/anura28/table_definitions/anura_CustomersMultiTimePeriod.json
cosmicfrog-1.0.31.dist-info/METADATA
cosmicfrog-1.0.31.dist-info/WHEEL
cosmicfrog-1.0.31.dist-info/top_level.txt
cosmicfrog-1.0.31.dist-info/RECORD
