Metadata-Version: 2.1
Name: cosmicfrog
Version: 1.0.31
Summary: Helpful utilities for working with Cosmic Frog models
Home-page: https://cosmicfrog.com
Author: Optilogic
License: MIT
Classifier: License :: OSI Approved :: MIT License
Classifier: Programming Language :: Python :: 3
Classifier: Operating System :: OS Independent
Requires-Python: >=3.11
Requires-Dist: charset-normalizer>=3.4.4
Requires-Dist: numpy>=1.26.4
Requires-Dist: pandas>=2.3.3
Requires-Dist: sqlalchemy>=2.0.44
Requires-Dist: optilogic>=2.14.0
Requires-Dist: PyJWT>=2.10.1
Requires-Dist: httpx>=0.28.1
Requires-Dist: splitio-client>=9.7.0
Requires-Dist: opentelemetry-api==1.27.0
Requires-Dist: opentelemetry-sdk==1.27.0
Requires-Dist: azure-monitor-opentelemetry-exporter>=1.0.0b40
Requires-Dist: psycopg2-binary>=2.9.9
